cli/__init__.py
cli/main.py
cli/maker.py
cli/repo.py
cli/runcmd.py
cli/template.py
on_on-0.2.0.dist-info/LICENSE
on_on-0.2.0.dist-info/METADATA
on_on-0.2.0.dist-info/WHEEL
on_on-0.2.0.dist-info/entry_points.txt
on_on-0.2.0.dist-info/top_level.txt
on_on-0.2.0.dist-info/RECORD
